oldas/__init__.py
oldas/__main__.py
oldas/article_ids.py
oldas/articles.py
oldas/exceptions.py
oldas/folders.py
oldas/prefixes.py
oldas/py.typed
oldas/session.py
oldas/states.py
oldas/subscriptions.py
oldas/types.py
oldas/unread.py
oldas/user.py
oldas-0.11.0.dist-info/WHEEL
oldas-0.11.0.dist-info/METADATA
oldas-0.11.0.dist-info/RECORD
