Metadata-Version: 2.4
Name: oldas
Version: 0.11.0
Summary: An async-friendly wrapper library for the API of TheOldReader
Keywords: API,async,atom,client,Google Reader,library,RSS,TheOldReader
Author: Dave Pearson
Author-email: Dave Pearson <davep@davep.org>
License-Expression: MIT
Classifier: Development Status :: 4 - Beta
Classifier: Operating System :: OS Independent
Classifier: Programming Language :: Python :: 3 :: Only
Classifier: Programming Language :: Python :: 3
Classifier: Programming Language :: Python :: 3.11
Classifier: Programming Language :: Python :: 3.12
Classifier: Programming Language :: Python :: 3.13
Classifier: Programming Language :: Python :: 3.14
Classifier: Topic :: Software Development :: Libraries
Classifier: Typing :: Typed
Requires-Dist: httpx>=0.28.1
Requires-Python: >=3.11
Project-URL: Homepage, https://oldas.davep.dev/
Project-URL: Repository, https://github.com/davep/oldas
Project-URL: Documentation, https://oldas.davep.dev/
Project-URL: Source, https://github.com/davep/oldas
Project-URL: Issues, https://github.com/davep/oldas/issues
Project-URL: Discussions, https://github.com/davep/oldas/discussions
